[
  {
    "slug": "5th",
    "title": "记录：我的机械臂项目开发经历",
    "tags": [
      "机械臂",
      "robotarm",
      "上位机"
    ],
    "date": "2026-04-29T16:20",
    "summary": "",
    "hidden": false,
    "category": "开源"
  },
  {
    "slug": "liangan",
    "title": "从Steam解谜游戏《一路》谈起：如何用图论与BFS算法“降维打击”机械联动谜题",
    "tags": [],
    "date": "2026-04-15T18:21",
    "summary": "",
    "cover": "https://i.imgs.ovh/2026/04/29/jIOgsQ.webp",
    "hidden": false,
    "category": ""
  },
  {
    "slug": "1st",
    "title": "我做了一个「KeyCast（键影）」：专治不能粘贴的离线软件",
    "tags": [],
    "date": "2026-04-08T09:41",
    "summary": "先拿AI水一篇",
    "cover": "https://i.imgs.ovh/2026/04/08/ZHNpLF.jpeg",
    "hidden": false,
    "category": "代码实现"
  }
]